django_tenants/__init__.py
django_tenants/admin.py
django_tenants/app_settings.py
django_tenants/apps.py
django_tenants/backends/__init__.py
django_tenants/backends/postgresql/__init__.py
django_tenants/backends/postgresql/base.py
django_tenants/backends/postgresql/schema.py
django_tenants/cache.py
django_tenants/clone.py
django_tenants/files/__init__.py
django_tenants/files/storage.py
django_tenants/log.py
django_tenants/management/__init__.py
django_tenants/management/commands/__init__.py
django_tenants/management/commands/force_rls_policy_update.py
django_tenants/management/commands.ignore/__init__.py
django_tenants/management/commands.ignore/all_tenants_command.py
django_tenants/management/commands.ignore/clone_tenant.py
django_tenants/management/commands.ignore/collectstatic_schemas.py
django_tenants/management/commands.ignore/create_missing_schemas.py
django_tenants/management/commands.ignore/create_tenant.py
django_tenants/management/commands.ignore/create_tenant_superuser.py
django_tenants/management/commands.ignore/delete_tenant.py
django_tenants/management/commands.ignore/migrate.py
django_tenants/management/commands.ignore/migrate_schemas.py
django_tenants/management/commands.ignore/rename_schema.py
django_tenants/management/commands.ignore/tenant_command.py
django_tenants/middleware/__init__.py
django_tenants/middleware/default.py
django_tenants/middleware/main.py
django_tenants/middleware/subfolder.py
django_tenants/middleware/suspicious.py
django_tenants/migrations/0001_initial.py
django_tenants/migrations/0002_remove_tenant_is_main_remove_tenant_slug_and_more.py
django_tenants/migrations/0003_tenant_slug.py
django_tenants/migrations/0004_alter_tenant_slug.py
django_tenants/migrations/0005_remove_tenant_description_remove_tenant_name.py
django_tenants/migrations/__init__.py
django_tenants/models.py
django_tenants/routers.py
django_tenants/signals.py
django_tenants/staticfiles/__init__.py
django_tenants/staticfiles/finders.py
picatron_tenant-0.2.1.dist-info/LICENSE
picatron_tenant-0.2.1.dist-info/METADATA
picatron_tenant-0.2.1.dist-info/WHEEL
picatron_tenant-0.2.1.dist-info/RECORD
